{"SAAPS":
   { "uniprotac": "P12883",
     "resnum": 870,
     "native": "R",
     "mutant": "C",
     "pdbs"  : [
{"SAAP":
   { "file": "/acrm/data/pdb/pdb2fxm.ent",
     "pdbcode": "2fxm",
     "residue": "B870",
     "mutation": "C",
     "structuretype": "crystal",
     "resolution": "2.70A",
     "rfactor": "24.20%",
     "results": {
         "Binding": {"Binding-BOOL": "OK"},
         "BuriedCharge": {"BuriedCharge-NATIVE-CHARGE": "1", "BuriedCharge-MUTANT-CHARGE": "0", "BuriedCharge-BOOL": "OK", "BuriedCharge-RELACCESS": "42.718"},
         "CisPro": {"CisPro-BOOL": "OK", "CisPro-NATIVE": "ARG", "CisPro-OMEGA": "179.360"},
         "Clash": {"Clash-ENERGY": "-0.08", "Clash-BOOL": "OK"},
         "CorePhilic": {"CorePhilic-MUTANT-HPHOB": "0.04", "CorePhilic-BOOL": "OK", "CorePhilic-RELACCESS": "42.718", "CorePhilic-NATIVE-HPHOB": "-1.8"},
         "Glycine": {"Glycine-MUTANT-THRESHOLD": "", "Glycine-BOOL": "OK", "Glycine-NATIVE-THRESHOLD": "0.35", "Glycine-NATIVE-ENERGY": "", "Glycine-PSI": "-39.530", "Glycine-MUTANT-ENERGY": "", "Glycine-PHI": "-68.474", "Glycine-NATIVE-BOOL": "OK", "Glycine-MUTANT": "CYS", "Glycine-NATIVE": "ARG"},
         "HBonds": {"HBonds-ENERGY": "NULL", "HBonds-BOOL": "OK", "HBonds-ZVAL": "NULL", "HBonds-ATOM": "NULL", "HBonds-PARTNER-RES": "NULL", "HBonds-PARTNER-ATOM": "NULL"},
         "Impact": {"Impact-BOOL": "OK", "Impact-NSEQ": "9", "Impact-THRESHOLD": "0.79", "Impact-CONSSCORE": "0.612968940893696"},
         "Interface": {"Interface-BOOL": "BAD", "Interface-RELACCESS": "7.699", "Interface-RELACCESS-MOL": "42.718"},
         "Proline": {"Proline-MUTANT-THRESHOLD": "0.53", "Proline-BOOL": "OK", "Proline-NATIVE-THRESHOLD": "", "Proline-NATIVE-ENERGY": "", "Proline-PSI": "-39.530", "Proline-MUTANT-ENERGY": "", "Proline-PHI": "-68.474", "Proline-NATIVE-BOOL": "OK", "Proline-MUTANT": "CYS", "Proline-NATIVE": "ARG"},
         "SProtFT": {"SProtFT-BOOL": "OK", "SProtFT-FEATURES": "0000000000000", "SProtFT-NAMES": ""},
         "SSGeom": {"SSGeom-BOOL": "OK"},
         "SurfacePhobic": {"SurfacePhobic-MUTANT-HPHOB": "0.04", "SurfacePhobic-BOOL": "OK", "SurfacePhobic-RELACCESS": "42.718", "SurfacePhobic-NATIVE-HPHOB": "-1.8"},
         "Voids": {"Voids-MUTANT": [5.736,2.976,0,0,0,0,0,0,0,0], "Voids-MUTANT-LARGEST": "5.736000", "Voids-BOOL": "OK", "Voids-NATIVE": [5.829,5.736,2.976,0,0,0,0,0,0,0], "Voids-NATIVE-LARGEST": "5.829000"}
      }
   }
}
,
{"SAAP":
   { "file": "/acrm/data/pdb/pdb2fxo.ent",
     "pdbcode": "2fxo",
     "residue": "B870",
     "mutation": "C",
     "structuretype": "crystal",
     "resolution": "2.50A",
     "rfactor": "27.70%",
     "results": {
         "Binding": {"Binding-BOOL": "BAD"},
         "BuriedCharge": {"BuriedCharge-NATIVE-CHARGE": "1", "BuriedCharge-MUTANT-CHARGE": "0", "BuriedCharge-BOOL": "OK", "BuriedCharge-RELACCESS": "58.848"},
         "CisPro": {"CisPro-BOOL": "OK", "CisPro-NATIVE": "ARG", "CisPro-OMEGA": "175.165"},
         "Clash": {"Clash-ENERGY": "-1.80", "Clash-BOOL": "OK"},
         "CorePhilic": {"CorePhilic-MUTANT-HPHOB": "0.04", "CorePhilic-BOOL": "OK", "CorePhilic-RELACCESS": "58.848", "CorePhilic-NATIVE-HPHOB": "-1.8"},
         "Glycine": {"Glycine-MUTANT-THRESHOLD": "", "Glycine-BOOL": "OK", "Glycine-NATIVE-THRESHOLD": "0.35", "Glycine-NATIVE-ENERGY": "", "Glycine-PSI": "-59.891", "Glycine-MUTANT-ENERGY": "", "Glycine-PHI": "-50.429", "Glycine-NATIVE-BOOL": "OK", "Glycine-MUTANT": "CYS", "Glycine-NATIVE": "ARG"},
         "HBonds": {"HBonds-ENERGY": "NULL", "HBonds-BOOL": "BAD", "HBonds-ZVAL": "NULL", "HBonds-ATOM": "NE", "HBonds-PARTNER-RES": "A866", "HBonds-PARTNER-ATOM": "OG"},
         "Impact": {"Impact-BOOL": "OK", "Impact-NSEQ": "9", "Impact-THRESHOLD": "0.79", "Impact-CONSSCORE": "0.612968940893696"},
         "Interface": {"Interface-BOOL": "BAD", "Interface-RELACCESS": "16.757", "Interface-RELACCESS-MOL": "58.848"},
         "Proline": {"Proline-MUTANT-THRESHOLD": "0.53", "Proline-BOOL": "OK", "Proline-NATIVE-THRESHOLD": "", "Proline-NATIVE-ENERGY": "", "Proline-PSI": "-59.891", "Proline-MUTANT-ENERGY": "", "Proline-PHI": "-50.429", "Proline-NATIVE-BOOL": "OK", "Proline-MUTANT": "CYS", "Proline-NATIVE": "ARG"},
         "SProtFT": {"SProtFT-BOOL": "OK", "SProtFT-FEATURES": "0000000000000", "SProtFT-NAMES": ""},
         "SSGeom": {"SSGeom-BOOL": "OK"},
         "SurfacePhobic": {"SurfacePhobic-MUTANT-HPHOB": "0.04", "SurfacePhobic-BOOL": "OK", "SurfacePhobic-RELACCESS": "58.848", "SurfacePhobic-NATIVE-HPHOB": "-1.8"},
         "Voids": {"Voids-MUTANT": [9.737,8.877,7.702,5.965,3.914,3.642,2.780,0,0,0], "Voids-MUTANT-LARGEST": "9.737000", "Voids-BOOL": "OK", "Voids-NATIVE": [9.737,8.877,7.702,5.965,3.914,3.642,2.780,0,0,0], "Voids-NATIVE-LARGEST": "9.737000"}
      }
   }
}
,
{"SAAP":
   { "file": "/acrm/data/pdb/pdb2fxo.ent",
     "pdbcode": "2fxo",
     "residue": "C870",
     "mutation": "C",
     "structuretype": "crystal",
     "resolution": "2.50A",
     "rfactor": "27.70%",
     "results": {
         "Binding": {"Binding-BOOL": "BAD"},
         "BuriedCharge": {"BuriedCharge-NATIVE-CHARGE": "1", "BuriedCharge-MUTANT-CHARGE": "0", "BuriedCharge-BOOL": "OK", "BuriedCharge-RELACCESS": "61.075"},
         "CisPro": {"CisPro-BOOL": "OK", "CisPro-NATIVE": "ARG", "CisPro-OMEGA": "166.676"},
         "Clash": {"Clash-ENERGY": "-2.48", "Clash-BOOL": "OK"},
         "CorePhilic": {"CorePhilic-MUTANT-HPHOB": "0.04", "CorePhilic-BOOL": "OK", "CorePhilic-RELACCESS": "61.075", "CorePhilic-NATIVE-HPHOB": "-1.8"},
         "Glycine": {"Glycine-MUTANT-THRESHOLD": "", "Glycine-BOOL": "OK", "Glycine-NATIVE-THRESHOLD": "0.35", "Glycine-NATIVE-ENERGY": "", "Glycine-PSI": "-54.626", "Glycine-MUTANT-ENERGY": "", "Glycine-PHI": "-52.820", "Glycine-NATIVE-BOOL": "OK", "Glycine-MUTANT": "CYS", "Glycine-NATIVE": "ARG"},
         "HBonds": {"HBonds-ENERGY": "NULL", "HBonds-BOOL": "BAD", "HBonds-ZVAL": "NULL", "HBonds-ATOM": "NH1", "HBonds-PARTNER-RES": "D866", "HBonds-PARTNER-ATOM": "OG"},
         "Impact": {"Impact-BOOL": "OK", "Impact-NSEQ": "9", "Impact-THRESHOLD": "0.79", "Impact-CONSSCORE": "0.612968940893696"},
         "Interface": {"Interface-BOOL": "BAD", "Interface-RELACCESS": "23.662", "Interface-RELACCESS-MOL": "61.075"},
         "Proline": {"Proline-MUTANT-THRESHOLD": "0.53", "Proline-BOOL": "OK", "Proline-NATIVE-THRESHOLD": "", "Proline-NATIVE-ENERGY": "", "Proline-PSI": "-54.626", "Proline-MUTANT-ENERGY": "", "Proline-PHI": "-52.820", "Proline-NATIVE-BOOL": "OK", "Proline-MUTANT": "CYS", "Proline-NATIVE": "ARG"},
         "SProtFT": {"SProtFT-BOOL": "OK", "SProtFT-FEATURES": "0000000000000", "SProtFT-NAMES": ""},
         "SSGeom": {"SSGeom-BOOL": "OK"},
         "SurfacePhobic": {"SurfacePhobic-MUTANT-HPHOB": "0.04", "SurfacePhobic-BOOL": "OK", "SurfacePhobic-RELACCESS": "61.075", "SurfacePhobic-NATIVE-HPHOB": "-1.8"},
         "Voids": {"Voids-MUTANT": [10.098,5.590,4.574,3.321,0,0,0,0,0,0], "Voids-MUTANT-LARGEST": "10.098000", "Voids-BOOL": "OK", "Voids-NATIVE": [10.098,5.590,4.574,3.321,0,0,0,0,0,0], "Voids-NATIVE-LARGEST": "10.098000"}
      }
   }
}
,
{"SAAP":
   { "file": "/acrm/data/pdb/pdb3dtp.ent",
     "pdbcode": "3dtp",
     "residue": "A881",
     "mutation": "C",
     "structuretype": "ElectronMicroscopy",
     "resolution": "20.00A",
     "rfactor": "0.00%",
     "results": {
         "Binding": {"Binding-BOOL": "OK"},
         "BuriedCharge": {"BuriedCharge-NATIVE-CHARGE": "1", "BuriedCharge-MUTANT-CHARGE": "0", "BuriedCharge-BOOL": "OK", "BuriedCharge-RELACCESS": "58.185"},
         "CisPro": {"CisPro-BOOL": "OK", "CisPro-NATIVE": "ARG", "CisPro-OMEGA": "-168.529"},
         "Clash": {"Clash-ENERGY": "-0.96", "Clash-BOOL": "OK"},
         "CorePhilic": {"CorePhilic-MUTANT-HPHOB": "0.04", "CorePhilic-BOOL": "OK", "CorePhilic-RELACCESS": "58.185", "CorePhilic-NATIVE-HPHOB": "-1.8"},
         "Glycine": {"Glycine-MUTANT-THRESHOLD": "", "Glycine-BOOL": "OK", "Glycine-NATIVE-THRESHOLD": "0.35", "Glycine-NATIVE-ENERGY": "", "Glycine-PSI": "-57.664", "Glycine-MUTANT-ENERGY": "", "Glycine-PHI": "-65.245", "Glycine-NATIVE-BOOL": "OK", "Glycine-MUTANT": "CYS", "Glycine-NATIVE": "ARG"},
         "HBonds": {"HBonds-ENERGY": "NULL", "HBonds-BOOL": "OK", "HBonds-ZVAL": "NULL", "HBonds-ATOM": "NULL", "HBonds-PARTNER-RES": "NULL", "HBonds-PARTNER-ATOM": "NULL"},
         "Impact": {"Impact-BOOL": "OK", "Impact-NSEQ": "9", "Impact-THRESHOLD": "0.86", "Impact-CONSSCORE": "0.473573696571841"},
         "Interface": {"Interface-BOOL": "BAD", "Interface-RELACCESS": "10.130", "Interface-RELACCESS-MOL": "58.185"},
         "Proline": {"Proline-MUTANT-THRESHOLD": "0.53", "Proline-BOOL": "OK", "Proline-NATIVE-THRESHOLD": "", "Proline-NATIVE-ENERGY": "", "Proline-PSI": "-57.664", "Proline-MUTANT-ENERGY": "", "Proline-PHI": "-65.245", "Proline-NATIVE-BOOL": "OK", "Proline-MUTANT": "CYS", "Proline-NATIVE": "ARG"},
         "SProtFT": {"SProtFT-BOOL": "OK", "SProtFT-FEATURES": "0000000000000", "SProtFT-NAMES": ""},
         "SSGeom": {"SSGeom-BOOL": "OK"},
         "SurfacePhobic": {"SurfacePhobic-MUTANT-HPHOB": "0.04", "SurfacePhobic-BOOL": "OK", "SurfacePhobic-RELACCESS": "58.185", "SurfacePhobic-NATIVE-HPHOB": "-1.8"},
         "Voids": {"Voids-MUTANT": [770.254,657.136,652.882,273.035,270.671,244.437,236.248,227.549,173.492,164.999], "Voids-MUTANT-LARGEST": "770.254000", "Voids-BOOL": "OK", "Voids-NATIVE": [770.254,657.136,652.882,273.035,270.671,244.437,236.248,227.549,173.492,164.999], "Voids-NATIVE-LARGEST": "770.254000"}
      }
   }
}
,
{"SAAP":
   { "file": "/acrm/data/pdb/pdb3dtp.ent",
     "pdbcode": "3dtp",
     "residue": "B881",
     "mutation": "C",
     "structuretype": "ElectronMicroscopy",
     "resolution": "20.00A",
     "rfactor": "0.00%",
     "results": {
         "Binding": {"Binding-BOOL": "OK"},
         "BuriedCharge": {"BuriedCharge-NATIVE-CHARGE": "1", "BuriedCharge-MUTANT-CHARGE": "0", "BuriedCharge-BOOL": "OK", "BuriedCharge-RELACCESS": "52.285"},
         "CisPro": {"CisPro-BOOL": "OK", "CisPro-NATIVE": "ARG", "CisPro-OMEGA": "177.006"},
         "Clash": {"Clash-ENERGY": "-0.60", "Clash-BOOL": "OK"},
         "CorePhilic": {"CorePhilic-MUTANT-HPHOB": "0.04", "CorePhilic-BOOL": "OK", "CorePhilic-RELACCESS": "52.285", "CorePhilic-NATIVE-HPHOB": "-1.8"},
         "Glycine": {"Glycine-MUTANT-THRESHOLD": "", "Glycine-BOOL": "OK", "Glycine-NATIVE-THRESHOLD": "0.35", "Glycine-NATIVE-ENERGY": "", "Glycine-PSI": "-43.181", "Glycine-MUTANT-ENERGY": "", "Glycine-PHI": "-57.040", "Glycine-NATIVE-BOOL": "OK", "Glycine-MUTANT": "CYS", "Glycine-NATIVE": "ARG"},
         "HBonds": {"HBonds-ENERGY": "NULL", "HBonds-BOOL": "BAD", "HBonds-ZVAL": "NULL", "HBonds-ATOM": "H", "HBonds-PARTNER-RES": "B878", "HBonds-PARTNER-ATOM": "OE1"},
         "Impact": {"Impact-BOOL": "OK", "Impact-NSEQ": "9", "Impact-THRESHOLD": "0.86", "Impact-CONSSCORE": "0.473573696571841"},
         "Interface": {"Interface-BOOL": "BAD", "Interface-RELACCESS": "19.176", "Interface-RELACCESS-MOL": "52.285"},
         "Proline": {"Proline-MUTANT-THRESHOLD": "0.53", "Proline-BOOL": "OK", "Proline-NATIVE-THRESHOLD": "", "Proline-NATIVE-ENERGY": "", "Proline-PSI": "-43.181", "Proline-MUTANT-ENERGY": "", "Proline-PHI": "-57.040", "Proline-NATIVE-BOOL": "OK", "Proline-MUTANT": "CYS", "Proline-NATIVE": "ARG"},
         "SProtFT": {"SProtFT-BOOL": "OK", "SProtFT-FEATURES": "0000000000000", "SProtFT-NAMES": ""},
         "SSGeom": {"SSGeom-BOOL": "OK"},
         "SurfacePhobic": {"SurfacePhobic-MUTANT-HPHOB": "0.04", "SurfacePhobic-BOOL": "OK", "SurfacePhobic-RELACCESS": "52.285", "SurfacePhobic-NATIVE-HPHOB": "-1.8"},
         "Voids": {"Voids-MUTANT": [525.384,298.129,280.039,232.694,201.208,196.630,185.684,179.878,152.405,142.370], "Voids-MUTANT-LARGEST": "525.384000", "Voids-BOOL": "OK", "Voids-NATIVE": [525.384,298.129,280.039,232.694,201.208,196.630,185.684,179.878,152.405,142.370], "Voids-NATIVE-LARGEST": "525.384000"}
      }
   }
}
,
{"SAAP":
   { "file": "/acrm/data/pdb/pdb4p7h.ent",
     "pdbcode": "4p7h",
     "residue": "A873",
     "mutation": "C",
     "structuretype": "crystal",
     "resolution": "3.20A",
     "rfactor": "22.90%",
     "results": {
         "Binding": {"Binding-BOOL": "OK"},
         "BuriedCharge": {"BuriedCharge-NATIVE-CHARGE": "0", "BuriedCharge-MUTANT-CHARGE": "0", "BuriedCharge-BOOL": "OK", "BuriedCharge-RELACCESS": "8.957"},
         "CisPro": {"CisPro-BOOL": "OK", "CisPro-NATIVE": "SER", "CisPro-OMEGA": "-179.766"},
         "Clash": {"Clash-ENERGY": "-2.13", "Clash-BOOL": "OK"},
         "CorePhilic": {"CorePhilic-MUTANT-HPHOB": "0.04", "CorePhilic-BOOL": "OK", "CorePhilic-RELACCESS": "8.957", "CorePhilic-NATIVE-HPHOB": "-0.26"},
         "Glycine": {"Glycine-MUTANT-THRESHOLD": "", "Glycine-BOOL": "OK", "Glycine-NATIVE-THRESHOLD": "0.35", "Glycine-NATIVE-ENERGY": "", "Glycine-PSI": "-26.988", "Glycine-MUTANT-ENERGY": "", "Glycine-PHI": "-72.962", "Glycine-NATIVE-BOOL": "OK", "Glycine-MUTANT": "CYS", "Glycine-NATIVE": "SER"},
         "HBonds": {"HBonds-ENERGY": "NULL", "HBonds-BOOL": "BAD", "HBonds-ZVAL": "NULL", "HBonds-ATOM": "OG", "HBonds-PARTNER-RES": "A981", "HBonds-PARTNER-ATOM": "N"},
         "Impact": {"Impact-BOOL": "OK", "Impact-NSEQ": "9", "Impact-THRESHOLD": "0.79", "Impact-CONSSCORE": "0.612968940893696"},
         "Interface": {"Interface-BOOL": "OK", "Interface-RELACCESS": "8.957", "Interface-RELACCESS-MOL": "8.957"},
         "Proline": {"Proline-MUTANT-THRESHOLD": "0.53", "Proline-BOOL": "OK", "Proline-NATIVE-THRESHOLD": "", "Proline-NATIVE-ENERGY": "", "Proline-PSI": "-26.988", "Proline-MUTANT-ENERGY": "", "Proline-PHI": "-72.962", "Proline-NATIVE-BOOL": "OK", "Proline-MUTANT": "CYS", "Proline-NATIVE": "SER"},
         "SProtFT": {"SProtFT-BOOL": "OK", "SProtFT-FEATURES": "0000000000000", "SProtFT-NAMES": ""},
         "SSGeom": {"SSGeom-BOOL": "OK"},
         "SurfacePhobic": {"SurfacePhobic-MUTANT-HPHOB": "0.04", "SurfacePhobic-BOOL": "OK", "SurfacePhobic-RELACCESS": "8.957", "SurfacePhobic-NATIVE-HPHOB": "-0.26"},
         "Voids": {"Voids-MUTANT": [709.624,671.578,564.914,419.844,328.913,303.341,194.964,192.610,185.963,185.305], "Voids-MUTANT-LARGEST": "709.624000", "Voids-BOOL": "OK", "Voids-NATIVE": [709.624,671.578,564.914,419.844,328.913,303.341,194.964,192.610,185.963,185.305], "Voids-NATIVE-LARGEST": "709.624000"}
      }
   }
}
,
{"SAAP":
   { "file": "/acrm/data/pdb/pdb4p7h.ent",
     "pdbcode": "4p7h",
     "residue": "B873",
     "mutation": "C",
     "structuretype": "crystal",
     "resolution": "3.20A",
     "rfactor": "22.90%",
     "results": {
         "Binding": {"Binding-BOOL": "OK"},
         "BuriedCharge": {"BuriedCharge-NATIVE-CHARGE": "0", "BuriedCharge-MUTANT-CHARGE": "0", "BuriedCharge-BOOL": "OK", "BuriedCharge-RELACCESS": "7.571"},
         "CisPro": {"CisPro-BOOL": "OK", "CisPro-NATIVE": "SER", "CisPro-OMEGA": "179.507"},
         "Clash": {"Clash-ENERGY": "3.23", "Clash-BOOL": "OK"},
         "CorePhilic": {"CorePhilic-MUTANT-HPHOB": "0.04", "CorePhilic-BOOL": "OK", "CorePhilic-RELACCESS": "7.571", "CorePhilic-NATIVE-HPHOB": "-0.26"},
         "Glycine": {"Glycine-MUTANT-THRESHOLD": "", "Glycine-BOOL": "OK", "Glycine-NATIVE-THRESHOLD": "0.35", "Glycine-NATIVE-ENERGY": "", "Glycine-PSI": "-25.126", "Glycine-MUTANT-ENERGY": "", "Glycine-PHI": "-69.143", "Glycine-NATIVE-BOOL": "OK", "Glycine-MUTANT": "CYS", "Glycine-NATIVE": "SER"},
         "HBonds": {"HBonds-ENERGY": "NULL", "HBonds-BOOL": "BAD", "HBonds-ZVAL": "NULL", "HBonds-ATOM": "OG", "HBonds-PARTNER-RES": "B981", "HBonds-PARTNER-ATOM": "N"},
         "Impact": {"Impact-BOOL": "OK", "Impact-NSEQ": "9", "Impact-THRESHOLD": "0.79", "Impact-CONSSCORE": "0.612968940893696"},
         "Interface": {"Interface-BOOL": "OK", "Interface-RELACCESS": "7.571", "Interface-RELACCESS-MOL": "7.571"},
         "Proline": {"Proline-MUTANT-THRESHOLD": "0.53", "Proline-BOOL": "OK", "Proline-NATIVE-THRESHOLD": "", "Proline-NATIVE-ENERGY": "", "Proline-PSI": "-25.126", "Proline-MUTANT-ENERGY": "", "Proline-PHI": "-69.143", "Proline-NATIVE-BOOL": "OK", "Proline-MUTANT": "CYS", "Proline-NATIVE": "SER"},
         "SProtFT": {"SProtFT-BOOL": "OK", "SProtFT-FEATURES": "0000000000000", "SProtFT-NAMES": ""},
         "SSGeom": {"SSGeom-BOOL": "OK"},
         "SurfacePhobic": {"SurfacePhobic-MUTANT-HPHOB": "0.04", "SurfacePhobic-BOOL": "OK", "SurfacePhobic-RELACCESS": "7.571", "SurfacePhobic-NATIVE-HPHOB": "-0.26"},
         "Voids": {"Voids-MUTANT": [613.145,377.405,352.632,229.701,224.453,222.702,206.969,186.615,185.598,165.595], "Voids-MUTANT-LARGEST": "613.145000", "Voids-BOOL": "OK", "Voids-NATIVE": [613.145,377.405,352.632,229.701,224.453,222.702,206.969,186.615,185.598,165.595], "Voids-NATIVE-LARGEST": "613.145000"}
      }
   }
}
,
{"SAAP":
   { "file": "/acrm/data/pdb/pdb4pa0.ent",
     "pdbcode": "4pa0",
     "residue": "A873",
     "mutation": "C",
     "structuretype": "crystal",
     "resolution": "2.25A",
     "rfactor": "20.30%",
     "results": {
         "Binding": {"Binding-BOOL": "OK"},
         "BuriedCharge": {"BuriedCharge-NATIVE-CHARGE": "0", "BuriedCharge-MUTANT-CHARGE": "0", "BuriedCharge-BOOL": "OK", "BuriedCharge-RELACCESS": "11.556"},
         "CisPro": {"CisPro-BOOL": "OK", "CisPro-NATIVE": "SER", "CisPro-OMEGA": "-175.893"},
         "Clash": {"Clash-ENERGY": "-3.15", "Clash-BOOL": "OK"},
         "CorePhilic": {"CorePhilic-MUTANT-HPHOB": "0.04", "CorePhilic-BOOL": "OK", "CorePhilic-RELACCESS": "11.556", "CorePhilic-NATIVE-HPHOB": "-0.26"},
         "Glycine": {"Glycine-MUTANT-THRESHOLD": "", "Glycine-BOOL": "OK", "Glycine-NATIVE-THRESHOLD": "0.35", "Glycine-NATIVE-ENERGY": "", "Glycine-PSI": "-16.888", "Glycine-MUTANT-ENERGY": "", "Glycine-PHI": "-72.927", "Glycine-NATIVE-BOOL": "OK", "Glycine-MUTANT": "CYS", "Glycine-NATIVE": "SER"},
         "HBonds": {"HBonds-ENERGY": "NULL", "HBonds-BOOL": "BAD", "HBonds-ZVAL": "NULL", "HBonds-ATOM": "OG", "HBonds-PARTNER-RES": "A981", "HBonds-PARTNER-ATOM": "N"},
         "Impact": {"Impact-BOOL": "OK", "Impact-NSEQ": "9", "Impact-THRESHOLD": "0.79", "Impact-CONSSCORE": "0.612968940893696"},
         "Interface": {"Interface-BOOL": "OK", "Interface-RELACCESS": "11.556", "Interface-RELACCESS-MOL": "11.556"},
         "Proline": {"Proline-MUTANT-THRESHOLD": "0.53", "Proline-BOOL": "OK", "Proline-NATIVE-THRESHOLD": "", "Proline-NATIVE-ENERGY": "", "Proline-PSI": "-16.888", "Proline-MUTANT-ENERGY": "", "Proline-PHI": "-72.927", "Proline-NATIVE-BOOL": "OK", "Proline-MUTANT": "CYS", "Proline-NATIVE": "SER"},
         "SProtFT": {"SProtFT-BOOL": "OK", "SProtFT-FEATURES": "0000000000000", "SProtFT-NAMES": ""},
         "SSGeom": {"SSGeom-BOOL": "OK"},
         "SurfacePhobic": {"SurfacePhobic-MUTANT-HPHOB": "0.04", "SurfacePhobic-BOOL": "OK", "SurfacePhobic-RELACCESS": "11.556", "SurfacePhobic-NATIVE-HPHOB": "-0.26"},
         "Voids": {"Voids-MUTANT": [402.271,355.907,349.151,306.528,264.459,255.601,215.180,190.779,151.526,147.958], "Voids-MUTANT-LARGEST": "402.271000", "Voids-BOOL": "OK", "Voids-NATIVE": [402.271,355.907,349.151,306.528,264.459,255.601,215.180,190.779,151.526,147.958], "Voids-NATIVE-LARGEST": "402.271000"}
      }
   }
}
,
{"SAAP":
   { "file": "/acrm/data/pdb/pdb4pa0.ent",
     "pdbcode": "4pa0",
     "residue": "B884",
     "mutation": "C",
     "structuretype": "crystal",
     "resolution": "2.25A",
     "rfactor": "20.30%",
     "results": {
         "Binding": {"Binding-BOOL": "OK"},
         "BuriedCharge": {"BuriedCharge-NATIVE-CHARGE": "0", "BuriedCharge-MUTANT-CHARGE": "0", "BuriedCharge-BOOL": "OK", "BuriedCharge-RELACCESS": "34.286"},
         "CisPro": {"CisPro-BOOL": "OK", "CisPro-NATIVE": "THR", "CisPro-OMEGA": "172.025"},
         "Clash": {"Clash-ENERGY": "-1.83", "Clash-BOOL": "OK"},
         "CorePhilic": {"CorePhilic-MUTANT-HPHOB": "0.04", "CorePhilic-BOOL": "OK", "CorePhilic-RELACCESS": "34.286", "CorePhilic-NATIVE-HPHOB": "-0.18"},
         "Glycine": {"Glycine-MUTANT-THRESHOLD": "", "Glycine-BOOL": "OK", "Glycine-NATIVE-THRESHOLD": "0.35", "Glycine-NATIVE-ENERGY": "", "Glycine-PSI": "99.240", "Glycine-MUTANT-ENERGY": "", "Glycine-PHI": "-147.619", "Glycine-NATIVE-BOOL": "OK", "Glycine-MUTANT": "CYS", "Glycine-NATIVE": "THR"},
         "HBonds": {"HBonds-ENERGY": "NULL", "HBonds-BOOL": "OK", "HBonds-ZVAL": "NULL", "HBonds-ATOM": "NULL", "HBonds-PARTNER-RES": "NULL", "HBonds-PARTNER-ATOM": "NULL"},
         "Impact": {"Impact-BOOL": "OK", "Impact-NSEQ": "9", "Impact-THRESHOLD": "0.79", "Impact-CONSSCORE": "0.612968940893696"},
         "Interface": {"Interface-BOOL": "OK", "Interface-RELACCESS": "34.286", "Interface-RELACCESS-MOL": "34.286"},
         "Proline": {"Proline-MUTANT-THRESHOLD": "0.53", "Proline-BOOL": "OK", "Proline-NATIVE-THRESHOLD": "", "Proline-NATIVE-ENERGY": "", "Proline-PSI": "99.240", "Proline-MUTANT-ENERGY": "", "Proline-PHI": "-147.619", "Proline-NATIVE-BOOL": "OK", "Proline-MUTANT": "CYS", "Proline-NATIVE": "THR"},
         "SProtFT": {"SProtFT-BOOL": "OK", "SProtFT-FEATURES": "0000000000000", "SProtFT-NAMES": ""},
         "SSGeom": {"SSGeom-BOOL": "OK"},
         "SurfacePhobic": {"SurfacePhobic-MUTANT-HPHOB": "0.04", "SurfacePhobic-BOOL": "OK", "SurfacePhobic-RELACCESS": "34.286", "SurfacePhobic-NATIVE-HPHOB": "-0.18"},
         "Voids": {"Voids-MUTANT": [495.316,250.645,190.680,167.761,163.751,151.041,144.767,135.919,132.308,124.602], "Voids-MUTANT-LARGEST": "495.316000", "Voids-BOOL": "OK", "Voids-NATIVE": [495.316,250.645,190.680,167.761,163.751,151.041,144.767,135.919,132.308,124.602], "Voids-NATIVE-LARGEST": "495.316000"}
      }
   }
}
,
{"SAAP":
   { "file": "/acrm/data/pdb/pdb5tby.ent",
     "pdbcode": "5tby",
     "residue": "A870",
     "mutation": "C",
     "structuretype": "ElectronMicroscopy",
     "resolution": "20.00A",
     "rfactor": "0.00%",
     "results": {
         "Binding": {"Binding-BOOL": "OK"},
         "BuriedCharge": {"BuriedCharge-NATIVE-CHARGE": "1", "BuriedCharge-MUTANT-CHARGE": "0", "BuriedCharge-BOOL": "OK", "BuriedCharge-RELACCESS": "52.749"},
         "CisPro": {"CisPro-BOOL": "OK", "CisPro-NATIVE": "ARG", "CisPro-OMEGA": "-179.014"},
         "Clash": {"Clash-ENERGY": "-0.64", "Clash-BOOL": "OK"},
         "CorePhilic": {"CorePhilic-MUTANT-HPHOB": "0.04", "CorePhilic-BOOL": "OK", "CorePhilic-RELACCESS": "52.749", "CorePhilic-NATIVE-HPHOB": "-1.8"},
         "Glycine": {"Glycine-MUTANT-THRESHOLD": "", "Glycine-BOOL": "OK", "Glycine-NATIVE-THRESHOLD": "0.35", "Glycine-NATIVE-ENERGY": "", "Glycine-PSI": "-24.819", "Glycine-MUTANT-ENERGY": "", "Glycine-PHI": "-71.687", "Glycine-NATIVE-BOOL": "OK", "Glycine-MUTANT": "CYS", "Glycine-NATIVE": "ARG"},
         "HBonds": {"HBonds-ENERGY": "NULL", "HBonds-BOOL": "OK", "HBonds-ZVAL": "NULL", "HBonds-ATOM": "NULL", "HBonds-PARTNER-RES": "NULL", "HBonds-PARTNER-ATOM": "NULL"},
         "Impact": {"Impact-BOOL": "OK", "Impact-NSEQ": "9", "Impact-THRESHOLD": "0.79", "Impact-CONSSCORE": "0.612968940893696"},
         "Interface": {"Interface-BOOL": "BAD", "Interface-RELACCESS": "10.014", "Interface-RELACCESS-MOL": "52.749"},
         "Proline": {"Proline-MUTANT-THRESHOLD": "0.53", "Proline-BOOL": "OK", "Proline-NATIVE-THRESHOLD": "", "Proline-NATIVE-ENERGY": "", "Proline-PSI": "-24.819", "Proline-MUTANT-ENERGY": "", "Proline-PHI": "-71.687", "Proline-NATIVE-BOOL": "OK", "Proline-MUTANT": "CYS", "Proline-NATIVE": "ARG"},
         "SProtFT": {"SProtFT-BOOL": "OK", "SProtFT-FEATURES": "0000000000000", "SProtFT-NAMES": ""},
         "SSGeom": {"SSGeom-BOOL": "OK"},
         "SurfacePhobic": {"SurfacePhobic-MUTANT-HPHOB": "0.04", "SurfacePhobic-BOOL": "OK", "SurfacePhobic-RELACCESS": "52.749", "SurfacePhobic-NATIVE-HPHOB": "-1.8"},
         "Voids": {"Voids-MUTANT": [656.460,614.732,332.312,303.007,189.475,155.964,128.932,119.052,86.483,84.523], "Voids-MUTANT-LARGEST": "656.460000", "Voids-BOOL": "OK", "Voids-NATIVE": [656.460,614.732,332.312,303.007,189.475,155.964,128.932,119.052,86.483,84.523], "Voids-NATIVE-LARGEST": "656.460000"}
      }
   }
}
,
{"SAAP":
   { "file": "/acrm/data/pdb/pdb5tby.ent",
     "pdbcode": "5tby",
     "residue": "B870",
     "mutation": "C",
     "structuretype": "ElectronMicroscopy",
     "resolution": "20.00A",
     "rfactor": "0.00%",
     "results": {
         "Binding": {"Binding-BOOL": "OK"},
         "BuriedCharge": {"BuriedCharge-NATIVE-CHARGE": "1", "BuriedCharge-MUTANT-CHARGE": "0", "BuriedCharge-BOOL": "OK", "BuriedCharge-RELACCESS": "69.162"},
         "CisPro": {"CisPro-BOOL": "OK", "CisPro-NATIVE": "ARG", "CisPro-OMEGA": "168.247"},
         "Clash": {"Clash-ENERGY": "-0.48", "Clash-BOOL": "OK"},
         "CorePhilic": {"CorePhilic-MUTANT-HPHOB": "0.04", "CorePhilic-BOOL": "OK", "CorePhilic-RELACCESS": "69.162", "CorePhilic-NATIVE-HPHOB": "-1.8"},
         "Glycine": {"Glycine-MUTANT-THRESHOLD": "", "Glycine-BOOL": "OK", "Glycine-NATIVE-THRESHOLD": "0.35", "Glycine-NATIVE-ENERGY": "", "Glycine-PSI": "-42.604", "Glycine-MUTANT-ENERGY": "", "Glycine-PHI": "-30.945", "Glycine-NATIVE-BOOL": "OK", "Glycine-MUTANT": "CYS", "Glycine-NATIVE": "ARG"},
         "HBonds": {"HBonds-ENERGY": "NULL", "HBonds-BOOL": "OK", "HBonds-ZVAL": "NULL", "HBonds-ATOM": "NULL", "HBonds-PARTNER-RES": "NULL", "HBonds-PARTNER-ATOM": "NULL"},
         "Impact": {"Impact-BOOL": "OK", "Impact-NSEQ": "9", "Impact-THRESHOLD": "0.79", "Impact-CONSSCORE": "0.612968940893696"},
         "Interface": {"Interface-BOOL": "BAD", "Interface-RELACCESS": "22.096", "Interface-RELACCESS-MOL": "69.162"},
         "Proline": {"Proline-MUTANT-THRESHOLD": "0.53", "Proline-BOOL": "OK", "Proline-NATIVE-THRESHOLD": "", "Proline-NATIVE-ENERGY": "", "Proline-PSI": "-42.604", "Proline-MUTANT-ENERGY": "", "Proline-PHI": "-30.945", "Proline-NATIVE-BOOL": "OK", "Proline-MUTANT": "CYS", "Proline-NATIVE": "ARG"},
         "SProtFT": {"SProtFT-BOOL": "OK", "SProtFT-FEATURES": "0000000000000", "SProtFT-NAMES": ""},
         "SSGeom": {"SSGeom-BOOL": "OK"},
         "SurfacePhobic": {"SurfacePhobic-MUTANT-HPHOB": "0.04", "SurfacePhobic-BOOL": "OK", "SurfacePhobic-RELACCESS": "69.162", "SurfacePhobic-NATIVE-HPHOB": "-1.8"},
         "Voids": {"Voids-MUTANT": [1194.990,424.288,397.415,290.830,267.986,262.411,218.258,215.334,211.317,205.282], "Voids-MUTANT-LARGEST": "1194.990000", "Voids-BOOL": "OK", "Voids-NATIVE": [1194.990,424.288,397.415,290.830,267.986,262.411,218.258,215.334,211.317,205.282], "Voids-NATIVE-LARGEST": "1194.990000"}
      }
   }
}
      ]
   }
}
